isso/__init__.py
isso/compat.py
isso/config.py
isso/core.py
isso/defaults.ini
isso/dispatch.py
isso/migrate.py
isso/run.py
isso/wsgi.py
isso/css/admin.css
isso/css/isso.css
isso/db/__init__.py
isso/db/comments.py
isso/db/preferences.py
isso/db/spam.py
isso/db/threads.py
isso/ext/__init__.py
isso/ext/notifications.py
isso/img/isso.svg
isso/js/count.dev.js
isso/js/count.min.js
isso/js/embed.dev.js
isso/js/embed.min.js
isso/templates/admin.html
isso/templates/disabled.html
isso/templates/login.html
isso/utils/__init__.py
isso/utils/hash.py
isso/utils/html.py
isso/utils/http.py
isso/utils/parse.py
isso/views/__init__.py
isso/views/comments.py
isso_cn-0.12.3rc1.dist-info/LICENSE
isso_cn-0.12.3rc1.dist-info/METADATA
isso_cn-0.12.3rc1.dist-info/WHEEL
isso_cn-0.12.3rc1.dist-info/entry_points.txt
isso_cn-0.12.3rc1.dist-info/top_level.txt
isso_cn-0.12.3rc1.dist-info/RECORD
