Metadata-Version: 2.1
Name: isso-cn
Version: 0.12.3rc1
Summary: lightweight Disqus alternative
Home-page: https://github.com/staugur/isso-cn/
Author: Martin Zimmermann
Author-email: info@posativ.org
License: MIT
Platform: UNKNOWN
Classifier: Development Status :: 4 - Beta
Classifier: Topic :: Internet
Classifier: Topic :: Internet :: WWW/HTTP :: HTTP Servers
Classifier: Topic :: Internet :: WWW/HTTP :: WSGI :: Application
Classifier: License :: OSI Approved :: MIT License
Classifier: Programming Language :: Python :: 2.7
Classifier: Programming Language :: Python :: 3.4
Classifier: Programming Language :: Python :: 3.5
Classifier: Programming Language :: Python :: 3.6
Requires-Dist: itsdangerous
Requires-Dist: Jinja2
Requires-Dist: misaka (<3.0,>=2.0)
Requires-Dist: html5lib
Requires-Dist: werkzeug (>=0.9)
Requires-Dist: bleach
Requires-Dist: ipaddr (>=2.1) ; python_version=="2.7"
Requires-Dist: configparser ; python_version=="2.7"
